shreyascodes/__init__.py
shreyascodes-0.1.dist-info/License.txt
shreyascodes-0.1.dist-info/METADATA
shreyascodes-0.1.dist-info/WHEEL
shreyascodes-0.1.dist-info/top_level.txt
shreyascodes-0.1.dist-info/RECORD
