Metadata-Version: 2.1
Name: shreyascodes
Version: 0.1
Summary: this is made only for making work easy
Author: Shreyas Naik
License: MIT
License-File: License.txt
